odoo/addons/product_route_profile/README.rst
odoo/addons/product_route_profile/__init__.py
odoo/addons/product_route_profile/__manifest__.py
odoo/addons/product_route_profile/hooks.py
odoo/addons/product_route_profile/i18n/fr.po
odoo/addons/product_route_profile/i18n/it.po
odoo/addons/product_route_profile/i18n/nl.po
odoo/addons/product_route_profile/i18n/product_route_profile.pot
odoo/addons/product_route_profile/models/__init__.py
odoo/addons/product_route_profile/models/product_template.py
odoo/addons/product_route_profile/models/route_profile.py
odoo/addons/product_route_profile/models/stock_route.py
odoo/addons/product_route_profile/readme/CONFIGURE.md
odoo/addons/product_route_profile/readme/CONTRIBUTORS.md
odoo/addons/product_route_profile/readme/DESCRIPTION.md
odoo/addons/product_route_profile/readme/USAGE.md
odoo/addons/product_route_profile/security/ir.model.access.csv
odoo/addons/product_route_profile/static/description/icon.png
odoo/addons/product_route_profile/static/description/icon.svg
odoo/addons/product_route_profile/static/description/index.html
odoo/addons/product_route_profile/tests/__init__.py
odoo/addons/product_route_profile/tests/test_product_route_profile.py
odoo/addons/product_route_profile/views/product_template.xml
odoo/addons/product_route_profile/views/route_profile.xml
odoo_addon_product_route_profile-18.0.1.0.0.3.dist-info/METADATA
odoo_addon_product_route_profile-18.0.1.0.0.3.dist-info/WHEEL
odoo_addon_product_route_profile-18.0.1.0.0.3.dist-info/top_level.txt
odoo_addon_product_route_profile-18.0.1.0.0.3.dist-info/RECORD
